{
  "project_info": {
    "project_number": "233002367467",
    "project_id": "fire-store-e5379",
    "storage_bucket": "fire-store-e5379.appspot.com"
  },
  "client": [
    {
      "client_info": {
        "mobilesdk_app_id": "1:233002367467:android:98e5cb8c2ae3420ec101ae",
        "android_client_info": {
          "package_name": "com.example.complete_store_with_admin_panel"
        }
      },
      "oauth_client": [
        {
          "client_id": "233002367467-1nd99lb0jpphlbsdsd36imfphuqrlifg.apps.googleusercontent.com",
          "client_type": 3
        }
      ],
      "api_key": [
        {
          "current_key": "AIzaSyBr5oh_WLx732e2hvoycI_fuaIx_pcwwoE"
        }
      ],
      "services": {
        "appinvite_service": {
          "other_platform_oauth_client": [
            {
              "client_id": "233002367467-1nd99lb0jpphlbsdsd36imfphuqrlifg.apps.googleusercontent.com",
              "client_type": 3
            }
          ]
        }
      }
    }
  ],
  "configuration_version": "1"
}